{
	"id": "0dac1a1d",
	"title": {
		"de": "Gottes Zeit ist die allerbeste Zeit"
	},
	"attribution": [
		{
			"composer": "bach",
			"dates": {"premiered": 1708},
			"catalog": [{"scheme": "bwv", "number": "106"}]
		}
	],
	"form": "sacred cantata",
	"instrumentation": "soprano, alto, tenor, bass, choir (SATB), 2 alto recorders, 2 violas da gamba, continuo",
	"notes": "Also known as Actus tragicus",
	"movements": [
		{
			"title": "Sonatina",
			"form": "instrumental",
			"key": "Eb"
		},
		{
			"title": "Gottes Zeit ist die allerbeste Zeit",
			"form": "chorus",
			"key": "Eb"
		},
		{
			"title": "Ach, Herr, lehre uns bedenken",
			"form": "arioso",
			"soloists": "tenor",
			"key": "c"
		},
		{
			"title": "Bestelle dein Haus",
			"form": "aria",
			"soloists": "bass",
			"key": "c"
		},
		{
			"title": "Es ist der alte Bund / Ja, komm, Herr Jesu, komm!",
			"form": "chorus and solo",
			"key": "f"
		},
		{
			"title": "In deine Hände befehl ich meinen Geist",
			"form": "aria",
			"soloists": "alto",
			"key": "bb"
		},
		{
			"title": "Heute wirst du mit mir im Paradies sein",
			"form": "arioso and chorale",
			"soloists": "bass, alto",
			"key": "c"
		},
		{
			"title": "Glorie, Lob, Ehr und Herrlichkeit",
			"form": "chorus",
			"key": "Eb"
		}
	],
	"xref": {
		"wp": "BWV_106"
	}
}
