{
	"id": "c6d8816c",
	"title": {
		"de": "Dem Gerechten muß das Licht"
	},
	"attribution": [
		{
			"composer": "bach",
			"dates": {},
			"catalog": [
				{
					"scheme": "bwv",
					"number": "195"
				}
			]
		}
	],
	"form": "wedding cantata",
	"instrumentation": "soprano, bass, choir (SATB), 3 trumpets, timpani, 2 horns, 2 flutes, 2 oboes, 2 oboes d'amore, 2 violins, viola, violone, basso continuo",
	"notes": "Only incomplete scores from later performances in the 1740s have survived.",
	"sections": [
		{
			"title": "Part I",
			"movements": [
				{
					"title": "Dem Gerechten muss das Licht immer wieder aufgehen",
					"form": "chorus"
				},
				{
					"title": "Dem Freudenlicht gerechter Frommen",
					"form": "recitative",
					"soloists": "bass"
				},
				{
					"title": "Rühmet Gottes Güt und Treu",
					"form": "aria",
					"soloists": "bass"
				},
				{
					"title": "Wohlan, so knüpfet denn ein Band",
					"form": "recitative",
					"soloists": "soprano"
				},
				{
					"title": "Wir kommen, deine Heiligkeit",
					"form": "chorus"
				}
			]
		},
		{
			"title": "Part II",
			"movements": [
				{
					"title": "Nun danket all und bringet Ehr",
					"form": "chorale"
				}
			]
		}
	],
	"xref": {
		"wp": "BWV_195",
		"mb": "26bab3f1-14d6-4349-bae7-c23c08c3a56f"
	}
}
