{
	"id": "7f543a7d",
	"title": {
		"de": "Weinen, Klagen, Sorgen, Zagen"
	},
	"attribution": [
		{
			"composer": "bach",
			"dates": {
				"premiered": 1714
			},
			"catalog": [
				{
					"scheme": "bwv",
					"number": "12"
				}
			]
		}
	],
	"form": "sacred cantata",
	"key": "f",
	"instrumentation": "SSATB, choir, 2 oboes, bassoon, strings, continuo",
	"notes": "Composed for the third Sunday after Easter",
	"movements": [
		{
			"title": "Sinfonia",
			"form": "sinfonia"
		},
		{
			"title": "Weinen, Klagen, Sorgen, Zagen",
			"form": "chorus"
		},
		{
			"title": "Wir müssen durch viel Trübsal in das Reich Gottes eingehen",
			"form": "recitative",
			"soloists": "alto",
			"key": "c"
		},
		{
			"title": "Kreuz und Kronen sind verbunden",
			"form": "aria",
			"soloists": "alto",
			"key": "c"
		},
		{
			"title": "Ich folge Christo nach",
			"form": "aria",
			"soloists": "bass",
			"key": "Eb"
		},
		{
			"title": "Sei getreu, alle Pein",
			"form": "aria",
			"soloists": "tenor",
			"key": "g"
		},
		{
			"title": "Was Gott tut, das ist wohlgetan",
			"form": "chorale",
			"key": "Bb"
		}
	],
	"xref": {
		"oo": "9364",
		"wp": "BWV_12",
		"mb": "a5058c10-1d60-44a1-921c-e1c6c2a168fb"
	}
}
